kedro_airflow/__init__.py
kedro_airflow/airflow_dag_template.j2
kedro_airflow/grouping.py
kedro_airflow/plugin.py
kedro_airflow-0.10.0.dist-info/METADATA
kedro_airflow-0.10.0.dist-info/WHEEL
kedro_airflow-0.10.0.dist-info/entry_points.txt
kedro_airflow-0.10.0.dist-info/top_level.txt
kedro_airflow-0.10.0.dist-info/RECORD
