Metadata-Version: 2.4
Name: kedro-airflow
Version: 0.10.0
Summary: Kedro-Airflow makes it easy to deploy Kedro projects to Airflow
Author: Kedro
License: Apache Software License (Apache 2.0)
Project-URL: Source, https://github.com/kedro-org/kedro-plugins/tree/main/kedro-airflow
Project-URL: Documentation, https://github.com/kedro-org/kedro-plugins/blob/main/kedro-airflow/README.md
Project-URL: Tracker, https://github.com/kedro-org/kedro-plugins/issues
Requires-Python: >=3.9
Requires-Dist: kedro>=0.19.0
Requires-Dist: python-slugify>=4.0
Requires-Dist: semver>=2.10
Provides-Extra: test
Requires-Dist: apache-airflow<3.0; extra == "test"
Requires-Dist: behave; extra == "test"
Requires-Dist: coverage>=7.2.0; extra == "test"
Requires-Dist: kedro-datasets; extra == "test"
Requires-Dist: pytest; extra == "test"
Requires-Dist: pytest-cov; extra == "test"
Requires-Dist: pytest-mock; extra == "test"
Requires-Dist: pytest-xdist; extra == "test"
Requires-Dist: wheel; extra == "test"
Provides-Extra: lint
Requires-Dist: bandit; extra == "lint"
Requires-Dist: black~=22.0; extra == "lint"
Requires-Dist: detect-secrets~=1.5.0; extra == "lint"
Requires-Dist: mypy~=1.0; extra == "lint"
Requires-Dist: pre-commit>=2.9.2; extra == "lint"
Requires-Dist: ruff~=0.0.290; extra == "lint"
Requires-Dist: types-PyYAML; extra == "lint"
Requires-Dist: types-cachetools; extra == "lint"
Requires-Dist: types-toml; extra == "lint"
